Workbook

Sheet Start Here
A1: Budget Planner & Expense Tracker
A2: Quick Start Guide
A5: HOW TO USE THIS SPREADSHEET
A7: Step 1: Set Your Budget | B7: Go to the Monthly Budget tab and enter your planned income and expenses.
A8: Step 2: Log Expenses | B8: Go to the Expense Tracker tab and add each expense as it happens.
A9: Step 3: Track Bills | B9: Use the Bills Tracker tab to record recurring bills and mark them paid.
A10: Step 4: Monitor Debt | B10: Enter your debts in the Debt Tracker tab and track payoff progress.
A11: Step 5: Set Savings Goals | B11: Use the Savings Tracker tab to set and track savings goals.
A12: Step 6: View Dashboard | B12: Go to the Dashboard tab to see your complete financial picture.
A14: CURRENCY NOTE | B14: All amounts are in USD by default. Change the number format to your local currency.
A16: IMPORTANT WARNINGS
B17: - Do NOT edit cells with gray background (formula cells). They contain auto-calculations.
B18: - Only edit white or green-background input cells.
B19: - Keep category names consistent across tabs for formulas to work correctly.
B20: - Clear sample data before starting your own budget (delete rows in each tab).
A22: SETUP CHECKLIST
B23: [ ] Go to Monthly Budget and enter your planned amounts
B24: [ ] Review category names and customize if needed
B25: [ ] Clear sample data from Expense Tracker
B26: [ ] Clear sample data from Bills Tracker
B27: [ ] Clear sample data from Debt Tracker
B28: [ ] Clear sample data from Savings Tracker
B29: [ ] Check Dashboard to confirm values update correctly
A31: Support: If you find a broken formula or have questions, contact the seller. Digital products are non-refundable.
A33: NAVIGATION | B33: Click the sheet tabs at the bottom to switch sections.
A34: Monthly Budget
A35: Expense Tracker
A36: Bills Tracker
A37: Debt Tracker
A38: Savings Tracker
A39: Dashboard
A40: Tip: In Google Sheets, use the sheet tabs at the bottom to navigate.

Sheet Monthly Budget
A1: Category | B1: Type | C1: Planned Amount | D1: Actual Amount | E1: Difference | F1: Notes | G1: <-- Go to Start Here tab for instructions
A2: INCOME
A3: Salary | B3: Income | C3: 4500 | D3: =SUMIF('Expense Tracker'!C:C,A3,'Expense Tracker'!G:G) | E3: =C3-D3
A4: Freelance | B4: Income | C4: 800 | D4: =SUMIF('Expense Tracker'!C:C,A4,'Expense Tracker'!G:G) | E4: =C4-D4
A5: Side Hustle | B5: Income | C5: 200 | D5: =SUMIF('Expense Tracker'!C:C,A5,'Expense Tracker'!G:G) | E5: =C5-D5
A6: Total Income | C6: =SUM(C3:C5) | D6: =SUM(D3:D5) | E6: =C6-D6
A8: EXPENSES
A9: Housing | B9: Expense | C9: 1200 | D9: =SUMIF('Expense Tracker'!C:C,A9,'Expense Tracker'!G:G) | E9: =C9-D9
A10: Utilities | B10: Expense | C10: 200 | D10: =SUMIF('Expense Tracker'!C:C,A10,'Expense Tracker'!G:G) | E10: =C10-D10
A11: Groceries | B11: Expense | C11: 400 | D11: =SUMIF('Expense Tracker'!C:C,A11,'Expense Tracker'!G:G) | E11: =C11-D11
A12: Transport | B12: Expense | C12: 150 | D12: =SUMIF('Expense Tracker'!C:C,A12,'Expense Tracker'!G:G) | E12: =C12-D12
A13: Insurance | B13: Expense | C13: 150 | D13: =SUMIF('Expense Tracker'!C:C,A13,'Expense Tracker'!G:G) | E13: =C13-D13
A14: Healthcare | B14: Expense | C14: 100 | D14: =SUMIF('Expense Tracker'!C:C,A14,'Expense Tracker'!G:G) | E14: =C14-D14
A15: Entertainment | B15: Expense | C15: 100 | D15: =SUMIF('Expense Tracker'!C:C,A15,'Expense Tracker'!G:G) | E15: =C15-D15
A16: Dining Out | B16: Expense | C16: 150 | D16: =SUMIF('Expense Tracker'!C:C,A16,'Expense Tracker'!G:G) | E16: =C16-D16
A17: Shopping | B17: Expense | C17: 100 | D17: =SUMIF('Expense Tracker'!C:C,A17,'Expense Tracker'!G:G) | E17: =C17-D17
A18: Subscriptions | B18: Expense | C18: 50 | D18: =SUMIF('Expense Tracker'!C:C,A18,'Expense Tracker'!G:G) | E18: =C18-D18
A19: Education | B19: Expense | C19: 80 | D19: =SUMIF('Expense Tracker'!C:C,A19,'Expense Tracker'!G:G) | E19: =C19-D19
A20: Debt Payments | B20: Expense | C20: 200 | D20: =SUMIF('Expense Tracker'!C:C,A20,'Expense Tracker'!G:G) | E20: =C20-D20
A21: Miscellaneous | B21: Expense | C21: 100 | D21: =SUMIF('Expense Tracker'!C:C,A21,'Expense Tracker'!G:G) | E21: =C21-D21
A22: Total Expenses | C22: =SUM(C9:C21) | D22: =SUM(D9:D21) | E22: =C22-D22
A24: SAVINGS
A25: Emergency Fund | B25: Savings | C25: 500 | D25: =SUMIF('Expense Tracker'!C:C,A25,'Expense Tracker'!G:G) | E25: =C25-D25
A26: Total Savings | C26: =SUM(C25:C25) | D26: =SUM(D25:D25) | E26: =C26-D26

Sheet Expense Tracker
A1: Date | B1: Month | C1: Category | D1: Description | E1: Payment Method | F1: Planned/Unplanned | G1: Amount | H1: Notes | I1: <-- Go to Start Here tab for instructions
A2: 46174 | B2: =TEXT(A2,"MMMM") | C2: Housing | D2: Rent June | E2: Bank Transfer | F2: Planned | G2: 1200
A3: 46174 | B3: =TEXT(A3,"MMMM") | C3: Utilities | D3: Electricity bill | E3: Bank Transfer | F3: Planned | G3: 85
A4: 46175 | B4: =TEXT(A4,"MMMM") | C4: Groceries | D4: Weekly groceries | E4: Credit Card | F4: Planned | G4: 95
A5: 46176 | B5: =TEXT(A5,"MMMM") | C5: Transport | D5: Gas station | E5: Credit Card | F5: Planned | G5: 40
A6: 46177 | B6: =TEXT(A6,"MMMM") | C6: Dining | D6: Lunch with team | E6: Debit Card | F6: Unplanned | G6: 25
A7: 46178 | B7: =TEXT(A7,"MMMM") | C7: Subscriptions | D7: Netflix monthly | E7: Credit Card | F7: Planned | G7: 15
A8: 46179 | B8: =TEXT(A8,"MMMM") | C8: Groceries | D8: Weekend groceries | E8: Debit Card | F8: Planned | G8: 78
A9: 46180 | B9: =TEXT(A9,"MMMM") | C9: Entertainment | D9: Movie tickets | E9: Credit Card | F9: Unplanned | G9: 30
A10: 46181 | B10: =TEXT(A10,"MMMM") | C10: Utilities | D10: Internet bill | E10: Bank Transfer | F10: Planned | G10: 55
A11: 46183 | B11: =TEXT(A11,"MMMM") | C11: Shopping | D11: New running shoes | E11: Credit Card | F11: Unplanned | G11: 85
A12: 46185 | B12: =TEXT(A12,"MMMM") | C12: Health | D12: Pharmacy | E12: Debit Card | F12: Planned | G12: 25 | H12: Vitamins and first aid
A13: 46188 | B13: =TEXT(A13,"MMMM") | C13: Insurance | D13: Health insurance | E13: Bank Transfer | F13: Planned | G13: 150
A14: 46191 | B14: =TEXT(A14,"MMMM") | C14: Dining | D14: Dinner with friends | E14: Credit Card | F14: Unplanned | G14: 45
A15: 46193 | B15: =TEXT(A15,"MMMM") | C15: Transport | D15: Monthly transit pass | E15: Debit Card | F15: Planned | G15: 60
A16: 46195 | B16: =TEXT(A16,"MMMM") | C16: Education | D16: Online course | E16: Credit Card | F16: Planned | G16: 80 | H16: Python course
A17: 46198 | B17: =TEXT(A17,"MMMM") | C17: Groceries | D17: Weekly groceries | E17: Credit Card | F17: Planned | G17: 72
A18: 46201 | B18: =TEXT(A18,"MMMM") | C18: Subscriptions | D18: Spotify monthly | E18: Credit Card | F18: Planned | G18: 10
A19: 46202 | B19: =TEXT(A19,"MMMM") | C19: Entertainment | D19: Concert tickets | E19: Credit Card | F19: Unplanned | G19: 60

Sheet Bills Tracker
A1: Bill Name | B1: Due Date | C1: Amount | D1: Frequency | E1: Paid Status | F1: Payment Method | G1: Notes | H1: <-- Go to Start Here tab for instructions
A2: Rent | B2: 46174 | C2: 1200 | D2: Monthly | E2: Paid | F2: Bank Transfer
A3: Electricity | B3: 46183 | C3: 85 | D3: Monthly | E3: Paid | F3: Bank Transfer
A4: Internet | B4: 46188 | C4: 55 | D4: Monthly | E4: Paid | F4: Bank Transfer
A5: Health Insurance | B5: 46193 | C5: 150 | D5: Monthly | E5: Paid | F5: Bank Transfer
A6: Car Insurance | B6: 46193 | C6: 120 | D6: Quarterly | E6: Unpaid | F6: Bank Transfer
A7: Phone Plan | B7: 46198 | C7: 40 | D7: Monthly | E7: Unpaid | F7: Credit Card

Sheet Debt Tracker
A1: Debt Name | B1: Starting Balance | C1: Current Balance | D1: Minimum Payment | E1: Extra Payment | F1: Interest Rate | G1: Payoff Progress % | H1: <-- Go to Start Here tab for instructions
A2: Credit Card A | B2: 3200 | C2: 2100 | D2: 85 | E2: 50 | F2: 0.2299 | G2: =IFERROR((B2-C2)/B2,0)
A3: Student Loan | B3: 15000 | C3: 12000 | D3: 200 | E3: 100 | F3: 0.055 | G3: =IFERROR((B3-C3)/B3,0)
A4: Personal Loan | B4: 5000 | C4: 3000 | D4: 120 | E4: 0 | F4: 0.08 | G4: =IFERROR((B4-C4)/B4,0)

Sheet Savings Tracker
A1: Goal Name | B1: Target Amount | C1: Current Amount | D1: Monthly Contribution | E1: Progress % | F1: Target Date | G1: <-- Go to Start Here tab for instructions
A2: Emergency Fund | B2: 10000 | C2: 4500 | D2: 500 | E2: =IFERROR(C2/B2,0) | F2: 46387
A3: Vacation Fund | B3: 2500 | C3: 800 | D3: 200 | E3: =IFERROR(C3/B3,0) | F3: 46568
A4: New Laptop Fund | B4: 2000 | C4: 600 | D4: 150 | E4: =IFERROR(C4/B4,0) | F4: 46295

Sheet Dashboard
A1: Financial Dashboard | D1: <-- Go to Start Here tab for instructions
A3: Total Income | B3: =SUMIF('Monthly Budget'!B:B,"Income",'Monthly Budget'!C:C) | C3: All income from Salary, Freelance, Side Hustle (planned)
A5: Total Expenses | B5: =SUMIF('Monthly Budget'!B:B,"Expense",'Monthly Budget'!D:D) | C5: All spending tracked in Expense Tracker
A7: Net Savings | B7: =B3-B5 | C7: Income minus Expenses
A9: Savings Rate % | B9: =IFERROR(B7/B3,0) | C9: Net Savings ÷ Total Income
A11: Bills Due | B11: =COUNTIF('Bills Tracker'!E:E,"Unpaid") | C11: Unpaid bills requiring attention
A13: Debt Remaining | B13: =SUM('Debt Tracker'!C:C) | C13: Total outstanding debt balance
A15: Avg Savings Progress | B15: =AVERAGE('Savings Tracker'!E:E) | C15: Average % of savings targets achieved
A17: Top Spending Category
A20: Monthly Spending Summary
A21: Category | B21: Total Spent
A22: Housing | B22: =SUMIF('Expense Tracker'!C:C,A22,'Expense Tracker'!G:G)
A23: Utilities | B23: =SUMIF('Expense Tracker'!C:C,A23,'Expense Tracker'!G:G)
A24: Groceries | B24: =SUMIF('Expense Tracker'!C:C,A24,'Expense Tracker'!G:G)
A25: Transport | B25: =SUMIF('Expense Tracker'!C:C,A25,'Expense Tracker'!G:G)
A26: Insurance | B26: =SUMIF('Expense Tracker'!C:C,A26,'Expense Tracker'!G:G)
A27: Health | B27: =SUMIF('Expense Tracker'!C:C,A27,'Expense Tracker'!G:G)
A28: Entertainment | B28: =SUMIF('Expense Tracker'!C:C,A28,'Expense Tracker'!G:G)
A29: Dining | B29: =SUMIF('Expense Tracker'!C:C,A29,'Expense Tracker'!G:G)
A30: Subscriptions | B30: =SUMIF('Expense Tracker'!C:C,A30,'Expense Tracker'!G:G)
A31: Shopping | B31: =SUMIF('Expense Tracker'!C:C,A31,'Expense Tracker'!G:G)
A32: Education | B32: =SUMIF('Expense Tracker'!C:C,A32,'Expense Tracker'!G:G)
A33: Debt Payments | B33: =SUMIF('Expense Tracker'!C:C,A33,'Expense Tracker'!G:G)
... A35: Other | B35: =SUMIF('Expense Tracker'!C:C,A35,'Expense Tracker'!G:G)
A37: Monthly Income vs Expenses
A38: Metric | B38: Amount
A39: Income | B39: =B3
A40: Expenses | B40: =B5
A41: Net Savings | B41: =B7
