Workbook

Sheet Start Here
A1: Nivora Invoice Generator & Payment Tracker
A2: Excel + Google Sheets compatible | Formula-driven | No macros
A4: Quick Start
A5: 1. Go to the Settings tab to set your currency, default tax rate, and preferences.
A6: 2. Add your clients on the Clients tab (or use the sample data as a guide).
A7: 3. Create invoices using the Invoice Generator tab.
A8: 4. Track payments on the Payment Tracker tab.
A9: 5. View your dashboard for revenue, outstanding balances, and invoice status.
A11: Tab Guide
A12: Tab | B12: Purpose
A13: Start Here | B13: Setup instructions and navigation guide
A14: Dashboard | B14: Revenue summary, invoice status breakdown, top clients
A15: Clients | B15: Manage client information and status
A16: Invoice Register | B16: All invoices with auto-status tracking
A17: Payment Tracker | B17: Log payments linked to invoices
A18: Invoice Generator | B18: Create printable invoices with auto-calculations
A19: Settings | B19: Configure currency, tax rate, dropdown values
A21: Important Notes
A22: Gray cells contain formulas — do not edit them.
A23: Green/white cells are for your data — enter values here.
A24: Sample data is included as an example. Replace it with your own data.
A25: Always keep a backup of your workbook.
A26: For support: workbysar1@gmail.com
A28: © Nivora

Sheet Dashboard
A1: Nivora Invoice Generator & Payment Tracker
A3: Total Revenue | C3: Paid Revenue | E3: Outstanding Revenue | G3: Total Invoices
A4: =SUMIFS('Invoice Register'!J:J,'Invoice Register'!M:M,"<>Draft") | C4: =SUMIFS('Invoice Register'!J:J,'Invoice Register'!M:M,"Paid") | E4: =SUMIFS('Invoice Register'!L:L,'Invoice Register'!M:M,"Sent",'Invoice Register'!L:L,">0")+SUMIFS('Invoice Register'!L:L,'Invoice Register'!M:M,"Overdue",'Invoice Register'!L:L,">0")+SUMIFS('Invoice Register'!L:L,'Invoice Register'!M:M,"Partial",'Invoice Register'!L:L,">0") | G4: =COUNTIF('Invoice Register'!M:M,"<>")-1
A6: Paid Invoices | C6: Unpaid Invoices | E6: Overdue Invoices | G6: Active Clients
A7: =COUNTIFS('Invoice Register'!M:M,"Paid") | C7: =COUNTIFS('Invoice Register'!M:M,"Sent")+COUNTIFS('Invoice Register'!M:M,"Overdue")+COUNTIFS('Invoice Register'!M:M,"Partial")+COUNTIFS('Invoice Register'!M:M,"Draft") | E7: =COUNTIFS('Invoice Register'!M:M,"Overdue") | G7: =COUNTIFS(Clients!G:G,"Active")
A9: Average Invoice Value
A10: =IFERROR(SUMIFS('Invoice Register'!J:J,'Invoice Register'!M:M,"<>Draft")/COUNTIFS('Invoice Register'!M:M,"<>Draft"),0)
A13: Revenue by Month
A14: Month | D14: Revenue
A15: Jan 2025 | D15: =SUMIFS('Invoice Register'!J:J,'Invoice Register'!M:M,"<>Draft",'Invoice Register'!B:B,">="&DATE(2025,1,1),'Invoice Register'!B:B,"<"&DATE(2025,1+1,1))
A16: Feb 2025 | D16: =SUMIFS('Invoice Register'!J:J,'Invoice Register'!M:M,"<>Draft",'Invoice Register'!B:B,">="&DATE(2025,2,1),'Invoice Register'!B:B,"<"&DATE(2025,2+1,1))
A17: Mar 2025 | D17: =SUMIFS('Invoice Register'!J:J,'Invoice Register'!M:M,"<>Draft",'Invoice Register'!B:B,">="&DATE(2025,3,1),'Invoice Register'!B:B,"<"&DATE(2025,3+1,1))
A18: Apr 2025 | D18: =SUMIFS('Invoice Register'!J:J,'Invoice Register'!M:M,"<>Draft",'Invoice Register'!B:B,">="&DATE(2025,4,1),'Invoice Register'!B:B,"<"&DATE(2025,4+1,1))
A20: Invoice Status Breakdown
A21: Status | D21: Count
A22: Paid | D22: =COUNTIFS('Invoice Register'!M:M,"Paid")
A23: Sent | D23: =COUNTIFS('Invoice Register'!M:M,"Sent")
A24: Partial | D24: =COUNTIFS('Invoice Register'!M:M,"Partial")
A25: Overdue | D25: =COUNTIFS('Invoice Register'!M:M,"Overdue")
A26: Draft | D26: =COUNTIFS('Invoice Register'!M:M,"Draft")
A28: Top Clients by Revenue
A29: Client | E29: Revenue
A30: James Wilson | E30: =SUMIFS('Invoice Register'!J:J,'Invoice Register'!E:E,"James Wilson",'Invoice Register'!M:M,"<>Draft")
A31: Sarah Chen | E31: =SUMIFS('Invoice Register'!J:J,'Invoice Register'!E:E,"Sarah Chen",'Invoice Register'!M:M,"<>Draft")
A32: Marcus Johnson | E32: =SUMIFS('Invoice Register'!J:J,'Invoice Register'!E:E,"Marcus Johnson",'Invoice Register'!M:M,"<>Draft")
A33: Aisha Patel | E33: =SUMIFS('Invoice Register'!J:J,'Invoice Register'!E:E,"Aisha Patel",'Invoice Register'!M:M,"<>Draft")
A34: David Kim | E34: =SUMIFS('Invoice Register'!J:J,'Invoice Register'!E:E,"David Kim",'Invoice Register'!M:M,"<>Draft")
A35: Elena Rodriguez | E35: =SUMIFS('Invoice Register'!J:J,'Invoice Register'!E:E,"Elena Rodriguez",'Invoice Register'!M:M,"<>Draft")

Sheet Clients
A1: Client ID | B1: Client Name | C1: Company | D1: Email | E1: Phone | F1: Address | G1: Status | H1: Notes
A2: CL-001 | B2: Sarah Chen | C2: Chen Design Studio | D2: sarah@chendesign.com | E2: 555-0101 | F2: 123 Design St, San Francisco, CA 94102 | G2: Active | H2: Graphic design retainer
A3: CL-002 | B3: Marcus Johnson | C3: Johnson Consulting | D3: marcus@johnsonconsulting.com | E3: 555-0102 | F3: 456 Business Ave, Austin, TX 73301 | G3: Active | H3: Monthly strategy consulting
A4: CL-003 | B4: Elena Rodriguez | C4: Rodriguez Web Services | D4: elena@rodriguezweb.com | E4: 555-0103 | F4: 789 Tech Blvd, Miami, FL 33101 | G4: Active | H4: Web development projects
A5: CL-004 | B5: David Kim | C5: Kim & Co. Marketing | D5: david@kimmarketing.com | E5: 555-0104 | F5: 321 Market St, Chicago, IL 60601 | G5: Active | H5: SEO and content marketing
A6: CL-005 | B6: Aisha Patel | C6: Patel Digital Solutions | D6: aisha@pateldigital.com | E6: 555-0105 | F6: 654 Innovation Dr, Seattle, WA 98101 | G6: Active | H6: Digital transformation consulting
A7: CL-006 | B7: James Wilson | C7: Wilson Creative Agency | D7: james@wilsoncreative.com | E7: 555-0106 | F7: 987 Artisan Way, New York, NY 10001 | G7: Active | H7: Brand design and strategy
A8: CL-007 | B8: Priya Sharma | C8: Sharma Bookkeeping | D8: priya@sharmabooks.com | E8: 555-0107 | F8: 147 Finance St, Denver, CO 80201 | G8: Inactive | H8: Previous bookkeeping client
A9: CL-008 | B9: Carlos Mendez | C9: Mendez Tech Services | D9: carlos@mendezteck.com | E9: 555-0108 | F9: 258 Code Ln, Portland, OR 97201 | G9: Active | H9: IT support retainer
A10: CL-009 | B10: Olivia Thompson | C10: Thompson Freelance Writing | D10: olivia@thompsonwrite.com | E10: 555-0109 | F10: 369 Wordsmith Rd, Boston, MA 02101 | G10: Active | H10: Content writing projects
A11: CL-010 | B11: Ben Okafor | C11: Okafor Design Lab | D11: ben@okaforlab.com | E11: 555-0110 | F11: 741 Creative Ct, Atlanta, GA 30301 | G11: Archived | H11: Completed project work

Sheet Invoice Register
A1: Invoice ID | B1: Invoice Date | C1: Due Date | D1: Client ID | E1: Client Name | F1: Description | G1: Subtotal | H1: Tax Rate | I1: Tax Amount | J1: Total | K1: Amount Paid | L1: Outstanding | M1: Status
A2: INV-001 | B2: 45662 | C2: 45693 | D2: CL-001 | E2: Sarah Chen | F2: Brand identity design | G2: 1500 | H2: 0.1 | I2: =G2*H2 | J2: =G2+I2 | K2: 1650 | L2: =J2-K2 | M2: =IF(L2=0,"Paid",IF(TODAY()>C2,"Overdue",IF(K2>0,"Partial","Sent")))
A3: INV-002 | B3: 45665 | C3: 45696 | D3: CL-002 | E3: Marcus Johnson | F3: Q1 strategy consulting | G3: 2500 | H3: 0.1 | I3: =G3*H3 | J3: =G3+I3 | K3: 2750 | L3: =J3-K3 | M3: =IF(L3=0,"Paid",IF(TODAY()>C3,"Overdue",IF(K3>0,"Partial","Sent")))
A4: INV-003 | B4: 45669 | C4: 45700 | D4: CL-003 | E4: Elena Rodriguez | F4: Website redesign | G4: 1800 | H4: 0.1 | I4: =G4*H4 | J4: =G4+I4 | K4: 1980 | L4: =J4-K4 | M4: =IF(L4=0,"Paid",IF(TODAY()>C4,"Overdue",IF(K4>0,"Partial","Sent")))
A5: INV-004 | B5: 45672 | C5: 45703 | D5: CL-004 | E5: David Kim | F5: SEO audit and recommendations | G5: 3200 | H5: 0.1 | I5: =G5*H5 | J5: =G5+I5 | K5: 3520 | L5: =J5-K5 | M5: =IF(L5=0,"Paid",IF(TODAY()>C5,"Overdue",IF(K5>0,"Partial","Sent")))
A6: INV-005 | B6: 45677 | C6: 45708 | D6: CL-005 | E6: Aisha Patel | F6: Digital strategy workshop | G6: 2100 | H6: 0.1 | I6: =G6*H6 | J6: =G6+I6 | K6: 2310 | L6: =J6-K6 | M6: =IF(L6=0,"Paid",IF(TODAY()>C6,"Overdue",IF(K6>0,"Partial","Sent")))
A7: INV-006 | B7: 45682 | C7: 45713 | D7: CL-006 | E7: James Wilson | F7: Brand campaign Q1 | G7: 4000 | H7: 0.1 | I7: =G7*H7 | J7: =G7+I7 | K7: 2200 | L7: =J7-K7 | M7: =IF(L7=0,"Paid",IF(TODAY()>C7,"Overdue",IF(K7>0,"Partial","Sent")))
A8: INV-007 | B8: 45690 | C8: 45718 | D8: CL-001 | E8: Sarah Chen | F8: Website UI design | G8: 1600 | H8: 0.1 | I8: =G8*H8 | J8: =G8+I8 | K8: 1760 | L8: =J8-K8 | M8: =IF(L8=0,"Paid",IF(TODAY()>C8,"Overdue",IF(K8>0,"Partial","Sent")))
A9: INV-008 | B9: 45693 | C9: 45721 | D9: CL-008 | E9: Carlos Mendez | F9: IT infrastructure audit | G9: 950 | H9: 0.1 | I9: =G9*H9 | J9: =G9+I9 | K9: 1045 | L9: =J9-K9 | M9: =IF(L9=0,"Paid",IF(TODAY()>C9,"Overdue",IF(K9>0,"Partial","Sent")))
A10: INV-009 | B10: 45698 | C10: 45726 | D10: CL-009 | E10: Olivia Thompson | F10: Blog content package | G10: 750 | H10: 0.1 | I10: =G10*H10 | J10: =G10+I10 | K10: 825 | L10: =J10-K10 | M10: =IF(L10=0,"Paid",IF(TODAY()>C10,"Overdue",IF(K10>0,"Partial","Sent")))
A11: INV-010 | B11: 45700 | C11: 45728 | D11: CL-002 | E11: Marcus Johnson | F11: Market research report | G11: 2800 | H11: 0.1 | I11: =G11*H11 | J11: =G11+I11 | K11: 1400 | L11: =J11-K11 | M11: =IF(L11=0,"Paid",IF(TODAY()>C11,"Overdue",IF(K11>0,"Partial","Sent")))
A12: INV-011 | B12: 45706 | C12: 45734 | D12: CL-003 | E12: Elena Rodriguez | F12: API integration | G12: 1500 | H12: 0.1 | I12: =G12*H12 | J12: =G12+I12 | K12: 0 | L12: =J12-K12 | M12: =IF(L12=0,"Paid",IF(TODAY()>C12,"Overdue",IF(K12>0,"Partial","Sent")))
A13: INV-012 | B13: 45710 | C13: 45738 | D13: CL-006 | E13: James Wilson | F13: Q2 campaign planning | G13: 3500 | H13: 0.1 | I13: =G13*H13 | J13: =G13+I13 | K13: 0 | L13: =J13-K13 | M13: =IF(L13=0,"Paid",IF(TODAY()>C13,"Overdue",IF(K13>0,"Partial","Sent")))
... A26: INV-025 | B26: 45755 | C26: 46515 | D26: CL-008 | E26: Carlos Mendez | F26: Server maintenance contract | G26: 800 | H26: 0.1 | I26: =G26*H26 | J26: =G26+I26 | K26: 0 | L26: =J26-K26 | M26: =IF(L26=0,"Paid",IF(TODAY()>C26,"Overdue",IF(K26>0,"Partial","Sent")))

Sheet Payment Tracker
A1: Payment ID | B1: Invoice ID | C1: Client Name | D1: Payment Date | E1: Payment Method | F1: Amount | G1: Notes
A2: PAY-001 | B2: INV-001 | C2: Sarah Chen | D2: 45677 | E2: Bank Transfer | F2: 1650 | G2: Full payment
A3: PAY-002 | B3: INV-002 | C3: Marcus Johnson | D3: 45682 | E3: PayPal | F3: 2750 | G3: Invoice paid via PayPal
A4: PAY-003 | B4: INV-003 | C4: Elena Rodriguez | D4: 45689 | E4: Bank Transfer | F4: 1980 | G4: Wire transfer
A5: PAY-004 | B5: INV-004 | C5: David Kim | D5: 45693 | E5: Cheque | F5: 3520 | G5: Cheque received
A6: PAY-005 | B6: INV-005 | C6: Aisha Patel | D6: 45698 | E6: Bank Transfer | F6: 2310 | G6: Direct deposit
A7: PAY-006 | B7: INV-006 | C7: James Wilson | D7: 45703 | E7: PayPal | F7: 2200 | G7: Partial payment - Q1 campaign
A8: PAY-007 | B8: INV-007 | C8: Sarah Chen | D8: 45708 | E8: Bank Transfer | F8: 1760 | G8: Full payment
A9: PAY-008 | B9: INV-008 | C9: Carlos Mendez | D9: 45717 | E9: Cash | F9: 1045 | G9: Paid in cash
A10: PAY-009 | B10: INV-009 | C10: Olivia Thompson | D10: 45721 | E10: Bank Transfer | F10: 825 | G10: Full payment
A11: PAY-010 | B11: INV-010 | C11: Marcus Johnson | D11: 45717 | E11: PayPal | F11: 1400 | G11: Partial - dispute on remaining
A12: PAY-011 | B12: INV-015 | C12: Sarah Chen | D12: 46096 | E12: Bank Transfer | F12: 1540 | G12: Full payment received
A13: PAY-012 | B13: INV-016 | C13: Carlos Mendez | D13: 46101 | E13: Bank Transfer | F13: 1320 | G13: Full payment
... A16: PAY-015 | B16: INV-014 | C16: Aisha Patel | D16: 45731 | E16: Bank Transfer | F16: 1210 | G16: Partial payment

Sheet Invoice Generator
A1: INVOICE
A3: Invoice Number: | B3: INV-001 | C3: Invoice Date: | D3: 45809
C4: Due Date: | D4: 45839
A6: From
A7: Your Name / Company: | B7: Your Company Name
A8: Your Address: | B8: 123 Business St, City, State ZIP
A9: Bill To
A10: Client Name: | B10: Sarah Chen
A11: Company: | B11: Chen Design Studio
A12: Address: | B12: 123 Design St, San Francisco, CA 94102
A14: Line Items
A15: # | B15: Description | C15: Quantity | D15: Rate | E15: Amount
A16: 1 | B16: Web design services | C16: 40 | D16: 75 | E16: =C16*D16
A17: 2 | B17: UI/UX consultation | C17: 10 | D17: 150 | E17: =C17*D17
A18: 3 | B18: Project management | C18: 5 | D18: 100 | E18: =C18*D18
E19: =C19*D19
E20: =C20*D20
E21: =C21*D21
A22: Summary
A23: Subtotal: | D23: =SUM(E16:E20)
A24: Tax Rate: | D24: 0.1
A25: Tax Amount: | D25: =D24*D23
A26: Total: | D26: =D24+D25
A28: Payment Instructions
A29: Payment Methods Accepted: Bank Transfer, PayPal, Credit Card
A30: Payment Terms: Payment due within 30 days of invoice date.

Sheet Settings
A1: Settings
A2: Edit values below to customize your workbook.
A4: General Settings
A5: Currency Symbol | B5: $
A6: Default Tax Rate | B6: 0.1
A8: Invoice Status Values
A9: Status
A10: Sent
A11: Partial
A12: Paid
A13: Overdue
A14: Draft
A16: Payment Method Values
A17: Payment Method
A18: Bank Transfer
A19: PayPal
A20: Cash
... A29: Archived
